madness/__init__.py
madness/application.py
madness/context.py
madness/middleware.py
madness/routing.py
madness-0.7.0.dist-info/LICENSE
madness-0.7.0.dist-info/METADATA
madness-0.7.0.dist-info/WHEEL
madness-0.7.0.dist-info/top_level.txt
madness-0.7.0.dist-info/zip-safe
madness-0.7.0.dist-info/RECORD
